{"description": "...", "name": "SIRS_HBRS HFMD Japan", "type": "theta", "partition": {"variable_population": {"group": [{"id": "Japan__all", "population_id": ["Japan__all"]}]}, "variable_time_series": {"group": [{"id": "EV71_JAP__IASR__inc", "time_series_id": ["EV71_JAP__IASR__inc"]}, {"id": "CA16_JAP__IASR__inc", "time_series_id": ["CA16_JAP__IASR__inc"]}]}, "identical_population": {"group": [{"id": "all", "population_id": ["Japan__all"]}]}, "identical_time_series": {"group": [{"id": "all", "time_series_id": ["EV71_JAP__IASR__inc", "CA16_JAP__IASR__inc"]}]}}, "parameter": {"sigma": {"group": {"all": {"min": {"value": 0.10000000000000001}, "max": {"value": 0.97999999999999998}, "guess": {"value": 0.7573610888191743}, "sd_transf": {"value": 0.20000000000000001}, "prior": {"value": "uniform"}}}, "transformation": "logit", "partition_id": "identical_population"}, "v": {"group": {"all": {"min": {"value": 2.1499999999999999}, "max": {"value": 2.8100000000000001}, "guess": {"value": 2.4897397406105095}, "sd_transf": {"value": 0.040000000000000001}, "prior": {"value": "normal"}}}, "transformation": "log", "unit": "D", "type": "rate_as_duration", "partition_id": "identical_population"}, "d": {"group": {"all": {"min": {"value": 0.59999999999999998}, "max": {"value": 0.98999999999999999}, "guess": {"value": 0.8205449871151963}, "sd_transf": {"value": 0.040000000000000001}, "prior": {"value": "uniform"}}}, "transformation": "log", "partition_id": "identical_population"}, "r0_2": {"group": {"all": {"min": {"value": 2}, "max": {"value": 30}, "guess": {"value": 4.0379404900678244}, "sd_transf": {"value": 0.040000000000000001}, "prior": {"value": "uniform"}}}, "transformation": "log", "partition_id": "identical_population"}, "RS": {"group": {"all": {"min": {"value": 0.050000000000000003}, "max": {"value": 8}, "guess": {"value": 0.63467328239822762}, "sd_transf": {"value": 0.20000000000000001}, "prior": {"value": "uniform"}}}, "transformation": "scale_pow10_neg", "partition_id": "identical_population"}, "SI": {"group": {"all": {"min": {"value": 3}, "max": {"value": 9}, "guess": {"value": 3.1909406990474065}, "sd_transf": {"value": 0.20000000000000001}, "prior": {"value": "uniform"}}}, "transformation": "scale_pow10_neg", "partition_id": "identical_population"}, "iota_1": {"group": {"all": {"min": {"value": -3.5}, "max": {"value": 4}, "guess": {"value": -0.89792444021899132}, "sd_transf": {"value": 0.040000000000000001}, "prior": {"value": "uniform"}}}, "transformation": "scale_pow10_bounded", "partition_id": "identical_population"}, "IS": {"group": {"all": {"min": {"value": 3}, "max": {"value": 9}, "guess": {"value": 3.1651002847456016}, "sd_transf": {"value": 0.20000000000000001}, "prior": {"value": "uniform"}}}, "transformation": "scale_pow10_neg", "partition_id": "identical_population"}, "SS": {"group": {"all": {"min": {"value": 0.050000000000000003}, "max": {"value": 8}, "guess": {"value": 1.1267503475555647}, "sd_transf": {"value": 0.20000000000000001}, "prior": {"value": "uniform"}}}, "transformation": "scale_pow10_neg", "partition_id": "identical_population"}, "rep": {"group": {"EV71_JAP__IASR__inc": {"min": {"value": 0.050000000000000003}, "max": {"value": 0.29999999999999999}, "guess": {"value": 0.009261111991485365}, "sd_transf": {"value": 0.20000000000000001}, "prior": {"value": "normal"}}, "CA16_JAP__IASR__inc": {"min": {"value": 0.050000000000000003}, "max": {"value": 0.29999999999999999}, "guess": {"value": 0.0040320127319340079}, "sd_transf": {"value": 0.20000000000000001}, "prior": {"value": "normal"}}}, "transformation": "logit", "partition_id": "variable_time_series"}, "IR": {"group": {"all": {"min": {"value": 0}, "max": {"value": 0}, "guess": {"value": 0.0}, "sd_transf": {"value": 0}, "prior": {"value": "uniform"}}}, "transformation": "logit", "partition_id": "identical_population"}, "e": {"group": {"all": {"min": {"value": 0.001}, "max": {"value": 0.29999999999999999}, "guess": {"value": 0.29028602226803668}, "sd_transf": {"value": 0.20000000000000001}, "prior": {"value": "uniform"}}}, "transformation": "logit", "partition_id": "identical_population"}, "SR": {"group": {"all": {"min": {"value": 0.050000000000000003}, "max": {"value": 8}, "guess": {"value": 0.61944091083039798}, "sd_transf": {"value": 0.20000000000000001}, "prior": {"value": "uniform"}}}, "transformation": "scale_pow10_neg", "partition_id": "identical_population"}, "r0_1": {"group": {"all": {"min": {"value": 2}, "max": {"value": 30}, "guess": {"value": 4.6112004621419675}, "sd_transf": {"value": 0.040000000000000001}, "prior": {"value": "uniform"}}}, "transformation": "log", "partition_id": "identical_population"}, "RI": {"group": {"all": {"min": {"value": 0}, "max": {"value": 0}, "guess": {"value": 0.0}, "sd_transf": {"value": 0}, "prior": {"value": "uniform"}}}, "transformation": "logit", "partition_id": "identical_population"}, "sto": {"group": {"all": {"min": {"value": 0}, "max": {"value": 0.80000000000000004}, "guess": {"value": 0.17186899999999999}, "sd_transf": {"value": 0.02}, "prior": {"value": "uniform"}}}, "transformation": "log", "partition_id": "identical_population"}, "g": {"group": {"all": {"min": {"value": 0.012500000000000001}, "max": {"value": 1}, "guess": {"value": 0.43732585122413659}, "sd_transf": {"value": 0.040000000000000001}, "prior": {"value": "uniform"}}}, "transformation": "log", "unit": "Y", "partition_id": "identical_population"}, "iota_2": {"group": {"all": {"min": {"value": -3.5}, "max": {"value": 4}, "guess": {"value": -0.68599351169771894}, "sd_transf": {"value": 0.040000000000000001}, "prior": {"value": "uniform"}}}, "transformation": "scale_pow10_bounded", "partition_id": "identical_population"}}}