{"description": "...", "name": "SIQRI_HBRS_B HFMD Japan", "type": "theta", "partition": {"variable_population": {"group": [{"id": "Japan__all", "population_id": ["Japan__all"]}]}, "variable_time_series": {"group": [{"id": "EV71_JAP__IASR__inc", "time_series_id": ["EV71_JAP__IASR__inc"]}, {"id": "CA16_JAP__IASR__inc", "time_series_id": ["CA16_JAP__IASR__inc"]}]}, "identical_population": {"group": [{"id": "all", "population_id": ["Japan__all"]}]}, "identical_time_series": {"group": [{"id": "all", "time_series_id": ["EV71_JAP__IASR__inc", "CA16_JAP__IASR__inc"]}]}}, "parameter": {"d": {"group": {"all": {"min": {"value": 0.59999999999999998}, "max": {"value": 0.98999999999999999}, "guess": {"value": 0.77806387286281475}, "sd_transf": {"value": 0.040000000000000001}, "prior": {"value": "uniform"}}}, "transformation": "log", "partition_id": "identical_population"}, "r0_2": {"group": {"all": {"min": {"value": 2}, "max": {"value": 30}, "guess": {"value": 20.250521231888516}, "sd_transf": {"value": 0.040000000000000001}, "prior": {"value": "uniform"}}}, "transformation": "log", "partition_id": "identical_population"}, "RS": {"group": {"all": {"min": {"value": 0.050000000000000003}, "max": {"value": 8}, "guess": {"value": 5.9834090081674232}, "sd_transf": {"value": 0.20000000000000001}, "prior": {"value": "uniform"}}}, "transformation": "scale_pow10_neg", "partition_id": "identical_population"}, "SI": {"group": {"all": {"min": {"value": 3}, "max": {"value": 9}, "guess": {"value": 8.9077162982327671}, "sd_transf": {"value": 0.20000000000000001}, "prior": {"value": "uniform"}}}, "transformation": "scale_pow10_neg", "partition_id": "identical_population"}, "iota_1": {"group": {"all": {"min": {"value": -3.5}, "max": {"value": 4}, "guess": {"value": -3.3521383875875257}, "sd_transf": {"value": 0.040000000000000001}, "prior": {"value": "uniform"}}}, "transformation": "scale_pow10_bounded", "partition_id": "identical_population"}, "IS": {"group": {"all": {"min": {"value": 3}, "max": {"value": 9}, "guess": {"value": 5.3414485650928212}, "sd_transf": {"value": 0.20000000000000001}, "prior": {"value": "uniform"}}}, "transformation": "scale_pow10_neg", "partition_id": "identical_population"}, "SS": {"group": {"all": {"min": {"value": 0.050000000000000003}, "max": {"value": 8}, "guess": {"value": 1.4038280280922282}, "sd_transf": {"value": 0.20000000000000001}, "prior": {"value": "uniform"}}}, "transformation": "scale_pow10_neg", "partition_id": "identical_population"}, "q": {"group": {"all": {"min": {"value": 0.050000000000000003}, "max": {"value": 12}, "guess": {"value": 6.6967744104508959}, "sd_transf": {"value": 0.040000000000000001}, "prior": {"value": "uniform"}}}, "transformation": "log", "unit": "M", "type": "rate_as_duration", "partition_id": "identical_population"}, "RI": {"group": {"all": {"min": {"value": 0}, "max": {"value": 0}, "guess": {"value": 0.0}, "sd_transf": {"value": 0}, "prior": {"value": "uniform"}}}, "transformation": "logit", "partition_id": "identical_population"}, "QS": {"group": {"all": {"min": {"value": 0}, "max": {"value": 0}, "guess": {"value": 0.0}, "sd_transf": {"value": 0}, "prior": {"value": "uniform"}}}, "transformation": "logit", "partition_id": "identical_population"}, "SR": {"group": {"all": {"min": {"value": 0.050000000000000003}, "max": {"value": 8}, "guess": {"value": 1.3441433291861242}, "sd_transf": {"value": 0.20000000000000001}, "prior": {"value": "uniform"}}}, "transformation": "scale_pow10_neg", "partition_id": "identical_population"}, "rep": {"group": {"EV71_JAP__IASR__inc": {"min": {"value": 0.050000000000000003}, "max": {"value": 0.29999999999999999}, "guess": {"value": 0.14732893332893066}, "sd_transf": {"value": 0.20000000000000001}, "prior": {"value": "normal"}}, "CA16_JAP__IASR__inc": {"min": {"value": 0.050000000000000003}, "max": {"value": 0.29999999999999999}, "guess": {"value": 0.15955412240704975}, "sd_transf": {"value": 0.20000000000000001}, "prior": {"value": "normal"}}}, "transformation": "logit", "partition_id": "variable_time_series"}, "e": {"group": {"all": {"min": {"value": 0.001}, "max": {"value": 0.29999999999999999}, "guess": {"value": 0.01897692998597144}, "sd_transf": {"value": 0.20000000000000001}, "prior": {"value": "uniform"}}}, "transformation": "logit", "partition_id": "identical_population"}, "IR": {"group": {"all": {"min": {"value": 0}, "max": {"value": 0}, "guess": {"value": 0.0}, "sd_transf": {"value": 0}, "prior": {"value": "uniform"}}}, "transformation": "logit", "partition_id": "identical_population"}, "z": {"group": {"all": {"min": {"value": 0}, "max": {"value": 0.94999999999999996}, "guess": {"value": 0.020622978497663164}, "sd_transf": {"value": 0.20000000000000001}, "prior": {"value": "uniform"}}}, "transformation": "logit", "partition_id": "identical_population"}, "r0_1": {"group": {"all": {"min": {"value": 2}, "max": {"value": 30}, "guess": {"value": 15.469718358176952}, "sd_transf": {"value": 0.040000000000000001}, "prior": {"value": "uniform"}}}, "transformation": "log", "partition_id": "identical_population"}, "QR": {"group": {"all": {"min": {"value": 0}, "max": {"value": 0}, "guess": {"value": 0.0}, "sd_transf": {"value": 0}, "prior": {"value": "uniform"}}}, "transformation": "logit", "partition_id": "identical_population"}, "SQ": {"group": {"all": {"min": {"value": 0}, "max": {"value": 0}, "guess": {"value": 0.0}, "sd_transf": {"value": 0}, "prior": {"value": "uniform"}}}, "transformation": "logit", "partition_id": "identical_population"}, "sigma": {"group": {"all": {"min": {"value": 0.10000000000000001}, "max": {"value": 0.97999999999999998}, "guess": {"value": 0.43375587948323369}, "sd_transf": {"value": 0.20000000000000001}, "prior": {"value": "uniform"}}}, "transformation": "logit", "partition_id": "identical_population"}, "RQ": {"group": {"all": {"min": {"value": 0}, "max": {"value": 0}, "guess": {"value": 0.0}, "sd_transf": {"value": 0}, "prior": {"value": "uniform"}}}, "transformation": "logit", "partition_id": "identical_population"}, "v": {"group": {"all": {"min": {"value": 2.1499999999999999}, "max": {"value": 2.8100000000000001}, "guess": {"value": 2.4091851583787123}, "sd_transf": {"value": 0.040000000000000001}, "prior": {"value": "normal"}}}, "transformation": "log", "unit": "D", "type": "rate_as_duration", "partition_id": "identical_population"}, "sto": {"group": {"all": {"min": {"value": 0}, "max": {"value": 0.80000000000000004}, "guess": {"value": 0.71606099999999995}, "sd_transf": {"value": 0.02}, "prior": {"value": "uniform"}}}, "transformation": "log", "partition_id": "identical_population"}, "iota_2": {"group": {"all": {"min": {"value": -3.5}, "max": {"value": 4}, "guess": {"value": 1.9906410433111859}, "sd_transf": {"value": 0.040000000000000001}, "prior": {"value": "uniform"}}}, "transformation": "scale_pow10_bounded", "partition_id": "identical_population"}}}