{"description": "...", "name": "SIRI_HBRS HFMD Japan", "type": "theta", "partition": {"variable_population": {"group": [{"id": "Japan__all", "population_id": ["Japan__all"]}]}, "variable_time_series": {"group": [{"id": "EV71_JAP__IASR__inc", "time_series_id": ["EV71_JAP__IASR__inc"]}, {"id": "CA16_JAP__IASR__inc", "time_series_id": ["CA16_JAP__IASR__inc"]}]}, "identical_population": {"group": [{"id": "all", "population_id": ["Japan__all"]}]}, "identical_time_series": {"group": [{"id": "all", "time_series_id": ["EV71_JAP__IASR__inc", "CA16_JAP__IASR__inc"]}]}}, "parameter": {"sigma": {"group": {"all": {"min": {"value": 0.10000000000000001}, "max": {"value": 0.97999999999999998}, "guess": {"value": 0.87361671089803183}, "sd_transf": {"value": 0.20000000000000001}, "prior": {"value": "uniform"}}}, "transformation": "logit", "partition_id": "identical_population"}, "v": {"group": {"all": {"min": {"value": 2.1499999999999999}, "max": {"value": 2.8100000000000001}, "guess": {"value": 2.4393807526644529}, "sd_transf": {"value": 0.040000000000000001}, "prior": {"value": "normal"}}}, "transformation": "log", "unit": "D", "type": "rate_as_duration", "partition_id": "identical_population"}, "d": {"group": {"all": {"min": {"value": 0.59999999999999998}, "max": {"value": 0.98999999999999999}, "guess": {"value": 0.67362766327872492}, "sd_transf": {"value": 0.040000000000000001}, "prior": {"value": "uniform"}}}, "transformation": "log", "partition_id": "identical_population"}, "r0_2": {"group": {"all": {"min": {"value": 2}, "max": {"value": 30}, "guess": {"value": 18.832838408497885}, "sd_transf": {"value": 0.040000000000000001}, "prior": {"value": "uniform"}}}, "transformation": "log", "partition_id": "identical_population"}, "RS": {"group": {"all": {"min": {"value": 0.050000000000000003}, "max": {"value": 8}, "guess": {"value": 2.6776998476253024}, "sd_transf": {"value": 0.20000000000000001}, "prior": {"value": "uniform"}}}, "transformation": "scale_pow10_neg", "partition_id": "identical_population"}, "SI": {"group": {"all": {"min": {"value": 3}, "max": {"value": 9}, "guess": {"value": 8.0341964213007984}, "sd_transf": {"value": 0.20000000000000001}, "prior": {"value": "uniform"}}}, "transformation": "scale_pow10_neg", "partition_id": "identical_population"}, "iota_1": {"group": {"all": {"min": {"value": -3.5}, "max": {"value": 4}, "guess": {"value": 3.8354804531547271}, "sd_transf": {"value": 0.040000000000000001}, "prior": {"value": "uniform"}}}, "transformation": "scale_pow10_bounded", "partition_id": "identical_population"}, "IS": {"group": {"all": {"min": {"value": 3}, "max": {"value": 9}, "guess": {"value": 8.1185170048622872}, "sd_transf": {"value": 0.20000000000000001}, "prior": {"value": "uniform"}}}, "transformation": "scale_pow10_neg", "partition_id": "identical_population"}, "SS": {"group": {"all": {"min": {"value": 0.050000000000000003}, "max": {"value": 8}, "guess": {"value": 2.2934100325823077}, "sd_transf": {"value": 0.20000000000000001}, "prior": {"value": "uniform"}}}, "transformation": "scale_pow10_neg", "partition_id": "identical_population"}, "rep": {"group": {"EV71_JAP__IASR__inc": {"min": {"value": 0.050000000000000003}, "max": {"value": 0.29999999999999999}, "guess": {"value": 0.041187490000112348}, "sd_transf": {"value": 0.20000000000000001}, "prior": {"value": "normal"}}, "CA16_JAP__IASR__inc": {"min": {"value": 0.050000000000000003}, "max": {"value": 0.29999999999999999}, "guess": {"value": 0.048130523219894951}, "sd_transf": {"value": 0.20000000000000001}, "prior": {"value": "normal"}}}, "transformation": "logit", "partition_id": "variable_time_series"}, "IR": {"group": {"all": {"min": {"value": 0}, "max": {"value": 0}, "guess": {"value": 0.0}, "sd_transf": {"value": 0}, "prior": {"value": "uniform"}}}, "transformation": "logit", "partition_id": "identical_population"}, "e": {"group": {"all": {"min": {"value": 0.001}, "max": {"value": 0.29999999999999999}, "guess": {"value": 0.29879982323585902}, "sd_transf": {"value": 0.20000000000000001}, "prior": {"value": "uniform"}}}, "transformation": "logit", "partition_id": "identical_population"}, "SR": {"group": {"all": {"min": {"value": 0.050000000000000003}, "max": {"value": 8}, "guess": {"value": 1.4890845149261827}, "sd_transf": {"value": 0.20000000000000001}, "prior": {"value": "uniform"}}}, "transformation": "scale_pow10_neg", "partition_id": "identical_population"}, "z": {"group": {"all": {"min": {"value": 0}, "max": {"value": 0.94999999999999996}, "guess": {"value": 0.028618043823623075}, "sd_transf": {"value": 0.20000000000000001}, "prior": {"value": "uniform"}}}, "transformation": "logit", "partition_id": "identical_population"}, "r0_1": {"group": {"all": {"min": {"value": 2}, "max": {"value": 30}, "guess": {"value": 15.464555407120642}, "sd_transf": {"value": 0.040000000000000001}, "prior": {"value": "uniform"}}}, "transformation": "log", "partition_id": "identical_population"}, "RI": {"group": {"all": {"min": {"value": 0}, "max": {"value": 0}, "guess": {"value": 0.0}, "sd_transf": {"value": 0}, "prior": {"value": "uniform"}}}, "transformation": "logit", "partition_id": "identical_population"}, "sto": {"group": {"all": {"min": {"value": 0}, "max": {"value": 0.80000000000000004}, "guess": {"value": 0.49215799999999998}, "sd_transf": {"value": 0.02}, "prior": {"value": "uniform"}}}, "transformation": "log", "partition_id": "identical_population"}, "iota_2": {"group": {"all": {"min": {"value": -3.5}, "max": {"value": 4}, "guess": {"value": 3.998280586161477}, "sd_transf": {"value": 0.040000000000000001}, "prior": {"value": "uniform"}}}, "transformation": "scale_pow10_bounded", "partition_id": "identical_population"}}}